odoo/addons/mgmtsystem_nonconformity_maintenance_equipment/README.rst
odoo/addons/mgmtsystem_nonconformity_maintenance_equipment/__init__.py
odoo/addons/mgmtsystem_nonconformity_maintenance_equipment/__manifest__.py
odoo/addons/mgmtsystem_nonconformity_maintenance_equipment/i18n/it.po
odoo/addons/mgmtsystem_nonconformity_maintenance_equipment/i18n/mgmtsystem_nonconformity_maintenance_equipment.pot
odoo/addons/mgmtsystem_nonconformity_maintenance_equipment/models/__init__.py
odoo/addons/mgmtsystem_nonconformity_maintenance_equipment/models/mgmtsystem_nonconformity.py
odoo/addons/mgmtsystem_nonconformity_maintenance_equipment/readme/CONTRIBUTORS.md
odoo/addons/mgmtsystem_nonconformity_maintenance_equipment/readme/DESCRIPTION.md
odoo/addons/mgmtsystem_nonconformity_maintenance_equipment/readme/USAGE.md
odoo/addons/mgmtsystem_nonconformity_maintenance_equipment/static/description/icon.png
odoo/addons/mgmtsystem_nonconformity_maintenance_equipment/static/description/index.html
odoo/addons/mgmtsystem_nonconformity_maintenance_equipment/views/mgmtsystem_nonconformity.xml
odoo_addon_mgmtsystem_nonconformity_maintenance_equipment-18.0.1.0.0.2.dist-info/METADATA
odoo_addon_mgmtsystem_nonconformity_maintenance_equipment-18.0.1.0.0.2.dist-info/WHEEL
odoo_addon_mgmtsystem_nonconformity_maintenance_equipment-18.0.1.0.0.2.dist-info/top_level.txt
odoo_addon_mgmtsystem_nonconformity_maintenance_equipment-18.0.1.0.0.2.dist-info/RECORD
